aisdecoder/__init__.py
aisdecoder/ais_kinematic_message.py
aisdecoder/ais_message.py
aisdecoder/ais_message_123.py
aisdecoder/ais_message_18.py
aisdecoder/ais_message_19.py
aisdecoder/ais_message_5.py
aisdecoder/correlate_static_iterator.py
aisdecoder/create_message_helper.py
aisdecoder/exceptions.py
aisdecoder/message_errors.py
aisdecoder/message_factory.py
aisdecoder/message_iterator.py
aisdecoder/mids.py
aisdecoder/sentence_correlation_queue.py
aisdecoder/sentence_error_report.py
aisdecoder/vdm_sentence.py
aisdecoder/vdm_sentence_factory.py
aisdecoder/vdm_sentence_structure.py
aisdecoder/basictypes/__init__.py
aisdecoder/basictypes/basic_types.py
aisdecoder/basictypes/mids.py
aisdecoder/basictypes/mmsi.py
aisdecoder/cli/main.py
aisdecoder/extras/singleton_decorator.py
aisdecoder/extras/swallow_exceptions.py
aisdecoder/filters/__init__.py
aisdecoder/filters/filter.py
aisdecoder/filters/filter_bbox.py
aisdecoder/writers/__init__.py
aisdecoder/writers/density_map.py
aisdecoder/writers/writer.py
aisdecoder/writers/writer_csv.py
aisdecoder/writers/writer_stats.py
aisdecoder-0.1.1.dist-info/METADATA
aisdecoder-0.1.1.dist-info/WHEEL
aisdecoder-0.1.1.dist-info/entry_points.txt
aisdecoder-0.1.1.dist-info/licenses/LICENSE
aisdecoder-0.1.1.dist-info/RECORD
